graph_clustering/__init__.py
graph_clustering/__version__.py
graph_clustering/install.py
graph_clustering-0.3.data/scripts/classify.py
graph_clustering-0.3.dist-info/DESCRIPTION.rst
graph_clustering-0.3.dist-info/METADATA
graph_clustering-0.3.dist-info/RECORD
graph_clustering-0.3.dist-info/WHEEL
graph_clustering-0.3.dist-info/metadata.json
graph_clustering-0.3.dist-info/top_level.txt
