Metadata-Version: 2.0
Name: graph-clustering
Version: 0.3
Summary: Clusters objects found in astronomical images by their visual similarity
Home-page: https://github.com/garrethmartin/HSC_UML
Author: garrethmartin
Author-email: g.martin4@herts.ac.uk
License: MIT
Platform: UNKNOWN
Classifier: License :: OSI Approved :: MIT License
Classifier: Programming Language :: Python
Classifier: Programming Language :: Python :: 2
Classifier: Programming Language :: Python :: 2.7
Classifier: Programming Language :: Python :: Implementation :: PyPy
Requires-Dist: astropy
Requires-Dist: configobj
Requires-Dist: joblib
Requires-Dist: matplotlib
Requires-Dist: numpy (>=1.14)
Requires-Dist: scipy (>=1.2)
Requires-Dist: sklearn
